aioevproc/__init__.py
aioevproc-0.1.0.dist-info/LICENSE
aioevproc-0.1.0.dist-info/METADATA
aioevproc-0.1.0.dist-info/WHEEL
aioevproc-0.1.0.dist-info/top_level.txt
aioevproc-0.1.0.dist-info/RECORD
