Metadata-Version: 2.1
Name: aioevproc
Version: 0.1.0
Summary: Minimal async/sync event processing framework on pure Python
Home-page: https://github.com/bryzgaloff/aioevproc
Author: Anton Bryzgalov
Author-email: tony.bryzgaloff@gmail.com
License: UNKNOWN
Platform: UNKNOWN
Classifier: Programming Language :: Python :: 3.8
Classifier: License :: OSI Approved :: MIT License
Classifier: Operating System :: OS Independent
Requires-Python: >=3.8
